CLIbrary/__init__.py
CLIbrary/__main__.py
CLIbrary/files.py
CLIbrary/inputs.py
CLIbrary/interface.py
CLIbrary/outputs.py
CLIbrary/settings.py
clibrary-1.10.0.dist-info/METADATA
clibrary-1.10.0.dist-info/WHEEL
clibrary-1.10.0.dist-info/licenses/LICENSE
clibrary-1.10.0.dist-info/RECORD
