Metadata-Version: 2.1
Name: CLIbrary
Version: 1.10.0
Summary: A comprehensive Python library of standard CLI utilities for convenient command, I/O, and file handling.
Project-URL: Homepage, https://github.com/diantonioandrea/CLIbrary
Project-URL: Documentation, https://github.com/diantonioandrea/CLIbrary/blob/main/docs/docs.md
Project-URL: Bug Tracker, https://github.com/diantonioandrea/CLIbrary/issues
Author-email: Andrea Di Antonio <mail@diantonioandrea.com>
License-File: LICENSE
Classifier: License :: OSI Approved :: GNU General Public License v3 (GPLv3)
Classifier: Operating System :: OS Independent
Classifier: Programming Language :: Python :: 3
Requires-Python: >=3.7
Requires-Dist: colorama
Requires-Dist: datetime
Requires-Dist: getkey
Requires-Dist: setuptools
